config_builder/__init__.py
config_builder/base_config_class.py
config_builder/config_builder.py
config_builder/flask_restx_utils.py
config_builder/json_encoding.py
config_builder/py.typed
config_builder/replacement_map.py
config_builder/utils.py
config_builder/yaml_constructors.py
yaml_config_builder-8.6.0.dist-info/LICENSE
yaml_config_builder-8.6.0.dist-info/METADATA
yaml_config_builder-8.6.0.dist-info/WHEEL
yaml_config_builder-8.6.0.dist-info/RECORD
