Metadata-Version: 2.1
Name: yaml-config-builder
Version: 8.6.0
Summary: Yaml-Config-Builder: SDK for building configuration classes on the basis of given content from YAML configuration files
Home-page: https://git.openlogisticsfoundation.org/silicon-economy/base/ml-toolbox/config-builder
License: Open Logistics Foundation License 1.3
Author: Maximilian Otten
Author-email: maximilian.otten@iml.fraunhofer.de
Requires-Python: >=3.8,<4.0
Classifier: Development Status :: 5 - Production/Stable
Classifier: Intended Audience :: Developers
Classifier: License :: Other/Proprietary License
Classifier: Natural Language :: English
Classifier: Programming Language :: Python :: 3
Classifier: Programming Language :: Python :: 3.8
Classifier: Programming Language :: Python :: 3.9
Classifier: Programming Language :: Python :: 3.10
Classifier: Programming Language :: Python :: 3.11
Provides-Extra: flask-restx-utils
Requires-Dist: PyYAML (>5.4)
Requires-Dist: attrs (>=20)
Requires-Dist: flask-restx (>=1.3) ; extra == "flask-restx-utils"
Requires-Dist: future (>0.18)
Requires-Dist: python-dateutil (>2.8)
Requires-Dist: related-mltoolbox (>=1.0.1,<2)
Project-URL: Documentation, https://git.openlogisticsfoundation.org/silicon-economy/base/ml-toolbox/config-builder/-/blob/main/documentation/index.adoc
Project-URL: Repository, https://git.openlogisticsfoundation.org/silicon-economy/base/ml-toolbox/config-builder
